{
  "english": "icy",
  "phat_am": "",
  "list_english": [
    {
      "type_word": "adjective",
      "list_definition": [
        {
          "mean_english": "cóng",
          "definition": "very cold",
          "world_new": [
            "cold"
          ],
          "list_ex_of_definition": [
            {
              "ex_of_definition": "icy winds."
            }
          ]
        },
        {
          "mean_english": "đóng băng",
          "definition": "covered with ice",
          "world_new": [
            "ice"
          ],
          "list_ex_of_definition": [
            {
              "ex_of_definition": "icy roads."
            }
          ]
        },
        {
          "mean_english": "không thân thiện",
          "definition": "unfriendly",
          "world_new": [
            "unfriendly"
          ],
          "list_ex_of_definition": [
            {
              "ex_of_definition": "an icy tone of voice.",
              "world_new": [
                "tone",
                "voice"
              ]
            }
          ]
        }
      ]
    }
  ],
  "list_ex_of_english": [
    "If they were preserved over geologic time, a record of past and present life may reside in the icy crust.",
    "The fact that half the fleet sailed in icy waters for more than 40 years explains the numbers of barque rigged sealers at the turn of the century.",
    "One minor omission in the book is that valley glaciers are a notable terrestrial icy environment where important findings were made during the infancy of biological research in ancient ice.",
    "When the icy cold comes to the one who can endure being out?",
    "A horse was 'rough shod' when the heads of the nails were left projecting from the shoe, to give a better grip in icy or muddy conditions.",
    "The attraction of any icy beginning is obvious, even if heterodox.",
    "The formation of polypeptides from single aminoacids was traced in simulation experiments representing the inner structure of icy dust grains.",
    "At the same time, he had to monitor fashion changes, lest he become old-fashioned and dowdy instead of an unapproachable, icy ideal."
  ],
  "list_see_also": [],
  "list_browse": [
    "iciness",
    "icing",
    "icon",
    "ICT",
    "icy",
    "ID",
    "idea",
    "ideal",
    "idealism"
  ],
  "list_img": [
    {
      "link_thumb": "https://live.staticflickr.com/65535/51809439843_ac10cc122d_n.jpg",
      "link_img": "https://live.staticflickr.com/65535/51809439843_1f751cddca_o.png",
      "id_image": "icy_2358552"
    }
  ]
}