{
  "english": "incognito",
  "phat_am": "iŋkoɡˈniːtəu",
  "list_english": [
    {
      "type_word": "adverb",
      "list_definition": [
        {
          "mean_english": "giấu tên",
          "definition": "without letting people know who one is, eg by using a false name",
          "world_new": [
            "people",
            "know",
            "false",
            "name"
          ],
          "list_ex_of_definition": [
            {
              "ex_of_definition": "He travelled incognito to Paris."
            }
          ]
        }
      ]
    }
  ],
  "list_ex_of_english": [
    "They would prefer to be incognito than enfranchised.",
    "In another interview we were told that he intends to travel incognito on the trains and tubes.",
    "Information about these events travelled by word of mouth (as well as the newly popular mobile phone) between clubbers who were obliged to party incognito.",
    "Who better than him to surpass the incognito signified in my girl of the cord?",
    "They are to devote more of their time to work on passenger ships and carry out many more spot and incognito checks than before.",
    "We should not he able to do this if we went incognito.",
    "The only way to make proper investigations was to go incognito.",
    "The vehicle inspectorate also makes incognito visits to testing stations; follows up complaints about stations; and checks vehicles at the roadside."
  ],
  "list_see_also": [],
  "list_browse": [
    "include",
    "including",
    "inclusion",
    "inclusive",
    "incognito",
    "incoherence",
    "incoherent",
    "incoherently",
    "incombustible"
  ],
  "list_img": [
    {
      "link_thumb": "https://live.staticflickr.com/65535/51808363797_a05577883f_n.jpg",
      "link_img": "https://live.staticflickr.com/65535/51808363797_574b4b0c97_o.png",
      "id_image": "incognito_3380363"
    },
    {
      "link_thumb": "https://live.staticflickr.com/65535/51810055730_d07450e799_n.jpg",
      "link_img": "https://live.staticflickr.com/65535/51810055730_503cd72afd_o.png",
      "id_image": "incognito_4001245"
    },
    {
      "link_thumb": "https://live.staticflickr.com/65535/51809673974_a152551c42_n.jpg",
      "link_img": "https://live.staticflickr.com/65535/51809673974_ce45ea2b20_o.png",
      "id_image": "incognito_4116611"
    }
  ]
}